Workbook

Sheet AR_Invoice_Master
A1: Invoice_ID | B1: Client_Name | C1: Invoice_Date | D1: Due_Date | E1: Invoice_Amount | F1: Amount_Paid | G1: Balance_Due
A2: INV-2026-001 | B2: Apex Global Consulting | C2: 46218 | D2: 46248 | E2: 15000 | F2: 15000 | G2: =E2-F2 -> 0
A3: INV-2026-002 | B3: Nexus Tech Solutions | C3: 46235 | D3: 46265 | E3: 22000 | F3: 5000 | G3: =E3-F3 -> 17000
A4: INV-2026-003 | B4: Quantum Logistics | C4: 46254 | D4: 46284 | E4: 18500 | F4: 0 | G4: =E4-F4 -> 18500
A5: INV-2026-004 | B5: Horizon Healthcare | C5: 46266 | D5: 46296 | E5: 34000 | F5: 0 | G5: =E5-F5 -> 34000
A6: INV-2026-005 | B6: Stellar Retail Group | C6: 46280 | D6: 46310 | E6: 12500 | F6: 0 | G6: =E6-F6 -> 12500
A7: INV-2026-006 | B7: Apex Global Consulting | C7: 46152 | D7: 46182 | E7: 28000 | F7: 0 | G7: =E7-F7 -> 28000

Sheet Aging_Analysis
A1: PROJECT 4.2: AR AGING ANALYSIS LEDGER
A2: Total Outstanding Balance: 110000 | C2: Total Overdue Balance: 97500 | E2: Average Days Sales Outstanding (DSO): 34.6
A5: Invoice_ID | B5: Client_Name | C5: Due_Date | D5: Balance_Due | E5: Days Overdue | F5: Aging_Bucket
A6: =AR_Invoice_Master!A2 -> INV-2026-001 | B6: =AR_Invoice_Master!B2 -> Apex Global Consulting | C6: =AR_Invoice_Master!D2 -> 46248 | D6: =AR_Invoice_Master!G2 -> 0 | E6: =IF(D6=0, 0, MAX(0, TODAY() - C6)) -> 0 | F6: {=_xlfn.IFS(D6=0, "PAID IN FULL", E6=0, "Current (Not Overdue)", E6<=30, "1–30 Days Overdue", E6<=60, "31–60 Days Overdue", E6<=90, "61–90 Days Overdue", TRUE, "90+ Days Overdue")} -> PAID IN FULL
A7: =AR_Invoice_Master!A3 -> INV-2026-002 | B7: =AR_Invoice_Master!B3 -> Nexus Tech Solutions | C7: =AR_Invoice_Master!D3 -> 46265 | D7: =AR_Invoice_Master!G3 -> 17000 | E7: =IF(D7=0, 0, MAX(0, TODAY() - C7)) -> 35 | F7: {=_xlfn.IFS(D7=0, "PAID IN FULL", E7=0, "Current (Not Overdue)", E7<=30, "1–30 Days Overdue", E7<=60, "31–60 Days Overdue", E7<=90, "61–90 Days Overdue", TRUE, "90+ Days Overdue")} -> 31–60 Days Overdue
A8: =AR_Invoice_Master!A4 -> INV-2026-003 | B8: =AR_Invoice_Master!B4 -> Quantum Logistics | C8: =AR_Invoice_Master!D4 -> 46284 | D8: =AR_Invoice_Master!G4 -> 18500 | E8: =IF(D8=0, 0, MAX(0, TODAY() - C8)) -> 16 | F8: {=_xlfn.IFS(D8=0, "PAID IN FULL", E8=0, "Current (Not Overdue)", E8<=30, "1–30 Days Overdue", E8<=60, "31–60 Days Overdue", E8<=90, "61–90 Days Overdue", TRUE, "90+ Days Overdue")} -> 1–30 Days Overdue
A9: =AR_Invoice_Master!A5 -> INV-2026-004 | B9: =AR_Invoice_Master!B5 -> Horizon Healthcare | C9: =AR_Invoice_Master!D5 -> 46296 | D9: =AR_Invoice_Master!G5 -> 34000 | E9: =IF(D9=0, 0, MAX(0, TODAY() - C9)) -> 4 | F9: {=_xlfn.IFS(D9=0, "PAID IN FULL", E9=0, "Current (Not Overdue)", E9<=30, "1–30 Days Overdue", E9<=60, "31–60 Days Overdue", E9<=90, "61–90 Days Overdue", TRUE, "90+ Days Overdue")} -> 1–30 Days Overdue
A10: =AR_Invoice_Master!A6 -> INV-2026-005 | B10: =AR_Invoice_Master!B6 -> Stellar Retail Group | C10: =AR_Invoice_Master!D6 -> 46310 | D10: =AR_Invoice_Master!G6 -> 12500 | E10: =IF(D10=0, 0, MAX(0, TODAY() - C10)) -> 0 | F10: {=_xlfn.IFS(D10=0, "PAID IN FULL", E10=0, "Current (Not Overdue)", E10<=30, "1–30 Days Overdue", E10<=60, "31–60 Days Overdue", E10<=90, "61–90 Days Overdue", TRUE, "90+ Days Overdue")} -> Current (Not Overdue)
A11: =AR_Invoice_Master!A7 -> INV-2026-006 | B11: =AR_Invoice_Master!B7 -> Apex Global Consulting | C11: =AR_Invoice_Master!D7 -> 46182 | D11: =AR_Invoice_Master!G7 -> 28000 | E11: =IF(D11=0, 0, MAX(0, TODAY() - C11)) -> 118 | F11: {=_xlfn.IFS(D11=0, "PAID IN FULL", E11=0, "Current (Not Overdue)", E11<=30, "1–30 Days Overdue", E11<=60, "31–60 Days Overdue", E11<=90, "61–90 Days Overdue", TRUE, "90+ Days Overdue")} -> 90+ Days Overdue

Sheet Cash_Flow_Forecaster
A1: AGING BUCKET RISK MATRIX
A2: Current (Not Overdue) | B2: 0.95
A3: 1–30 Days Overdue | B3: 0.8
A4: 31–60 Days Overdue | B4: 0.6
A5: 61–90 Days Overdue | B5: 0.3
A6: 90+ Days Overdue | B6: 0.1
A9: Invoice_ID | B9: Client_Name | C9: Balance_Due | D9: Aging_Bucket | E9: Collection_Prob_% | F9: Expected_Cash_Inflow | G9: Target_Week
A10: =AR_Invoice_Master!A2 -> INV-2026-001 | B10: =AR_Invoice_Master!B2 -> Apex Global Consulting | C10: =AR_Invoice_Master!G2 -> 0 | D10: =Aging_Analysis!F6 -> PAID IN FULL | E10: =IF(D10="PAID IN FULL", 1, _xlfn.XLOOKUP(D10, $A$2:$A$6, $B$2:$B$6, 0)) -> 1 | F10: =C10 * E10 -> 0 | G10: Week 1
A11: =AR_Invoice_Master!A3 -> INV-2026-002 | B11: =AR_Invoice_Master!B3 -> Nexus Tech Solutions | C11: =AR_Invoice_Master!G3 -> 17000 | D11: =Aging_Analysis!F7 -> 31–60 Days Overdue | E11: =IF(D11="PAID IN FULL", 1, _xlfn.XLOOKUP(D11, $A$2:$A$6, $B$2:$B$6, 0)) -> 0.6 | F11: =C11 * E11 -> 10200 | G11: Week 2
A12: =AR_Invoice_Master!A4 -> INV-2026-003 | B12: =AR_Invoice_Master!B4 -> Quantum Logistics | C12: =AR_Invoice_Master!G4 -> 18500 | D12: =Aging_Analysis!F8 -> 1–30 Days Overdue | E12: =IF(D12="PAID IN FULL", 1, _xlfn.XLOOKUP(D12, $A$2:$A$6, $B$2:$B$6, 0)) -> 0.8 | F12: =C12 * E12 -> 14800 | G12: Week 3
A13: =AR_Invoice_Master!A5 -> INV-2026-004 | B13: =AR_Invoice_Master!B5 -> Horizon Healthcare | C13: =AR_Invoice_Master!G5 -> 34000 | D13: =Aging_Analysis!F9 -> 1–30 Days Overdue | E13: =IF(D13="PAID IN FULL", 1, _xlfn.XLOOKUP(D13, $A$2:$A$6, $B$2:$B$6, 0)) -> 0.8 | F13: =C13 * E13 -> 27200 | G13: Week 4
A14: =AR_Invoice_Master!A6 -> INV-2026-005 | B14: =AR_Invoice_Master!B6 -> Stellar Retail Group | C14: =AR_Invoice_Master!G6 -> 12500 | D14: =Aging_Analysis!F10 -> Current (Not Overdue) | E14: =IF(D14="PAID IN FULL", 1, _xlfn.XLOOKUP(D14, $A$2:$A$6, $B$2:$B$6, 0)) -> 0.95 | F14: =C14 * E14 -> 11875 | G14: Week 5
A15: =AR_Invoice_Master!A7 -> INV-2026-006 | B15: =AR_Invoice_Master!B7 -> Apex Global Consulting | C15: =AR_Invoice_Master!G7 -> 28000 | D15: =Aging_Analysis!F11 -> 90+ Days Overdue | E15: =IF(D15="PAID IN FULL", 1, _xlfn.XLOOKUP(D15, $A$2:$A$6, $B$2:$B$6, 0)) -> 0.1 | F15: =C15 * E15 -> 2800 | G15: Week 6
B59: Invoice_ID | C59: Client_Name | D59: Balance_Due | E59: Aging_Bucket | F59: Collection_Prob_% | G59: Expected_Cash_Inflow | H59: Target_Week | J59: Forecast_Week | K59: Total_Expected_Inflow
B60: =AR_Invoice_Master!A2 -> INV-2026-001 | C60: =AR_Invoice_Master!B2 -> Apex Global Consulting | D60: =AR_Invoice_Master!G2 -> 0 | E60: =Aging_Analysis!F6 -> PAID IN FULL | F60: =IFERROR(VLOOKUP(E60, $A$2:$B$6, 2, FALSE), 0) -> 0 | G60: =D60 * F60 -> 0 | H60: Week 1 | J60: Week 1 | K60: =SUMIF($H$60:$H$65, J60, $G$60:$G$65) -> 0
B61: =AR_Invoice_Master!A3 -> INV-2026-002 | H61: Week 2 | J61: Week 2 | K61: =SUMIF($H$60:$H$65, J61, $G$60:$G$65) -> 0
B62: =AR_Invoice_Master!A4 -> INV-2026-003 | H62: Week 1 | J62: Week 3 | K62: =SUMIF($H$60:$H$65, J62, $G$60:$G$65) -> 0
B63: =AR_Invoice_Master!A5 -> INV-2026-004 | H63: Week 3 | J63: Week 4 | K63: =SUMIF($H$60:$H$65, J63, $G$60:$G$65) -> 0
B64: =AR_Invoice_Master!A6 -> INV-2026-005 | H64: Week 4 | J64: Week 5 | K64: =SUMIF($H$60:$H$65, J64, $G$60:$G$65) -> 0
B65: =AR_Invoice_Master!A7 -> INV-2026-006 | H65: Week 2 | J65: Week 6 | K65: =SUMIF($H$60:$H$65, J65, $G$60:$G$65) -> 0
J66: Week 7 | K66: =SUMIF($H$60:$H$65, J66, $G$60:$G$65) -> 0
J67: Week 8 | K67: =SUMIF($H$60:$H$65, J67, $G$60:$G$65) -> 0
J68: Week 9 | K68: =SUMIF($H$60:$H$65, J68, $G$60:$G$65) -> 0
J69: Week 10 | K69: =SUMIF($H$60:$H$65, J69, $G$60:$G$65) -> 0
J70: Week 11 | K70: =SUMIF($H$60:$H$65, J70, $G$60:$G$65) -> 0
J71: Week 12 | K71: =SUMIF($H$60:$H$65, J71, $G$60:$G$65) -> 0
J72: Week 13 | K72: =SUMIF($H$60:$H$65, J72, $G$60:$G$65) -> 0

Sheet Documentation_Setup
A1: PROJECT 4.2: ACCOUNTS RECEIVABLE AGING LEDGER & CASH FLOW FORECASTER
A2: 1. System Purpose | B2: Tracks open customer invoices, calculates aging risk buckets, computes Days Sales Outstanding (DSO), and projects 13-week probability-weighted cash inflows.
A4: 2. Key KPI Metric Summaries
A5: Total Portfolio Outstanding Balance | B5: =SUM(AR_Invoice_Master!G2:G7) -> 110000
A6: Total Overdue AR Exposure | B6: =Aging_Analysis!J31 -> 0
A7: Portfolio Days Sales Outstanding (DSO) | B7: =Aging_Analysis!K31 -> 0
A8: Total Expected Cash Inflow (Probability-Adjusted) | B8: =SUM(Cash_Flow_Forecaster!G60:G65) -> 0
A10: 3. Core Mathematical Formulas
A11: Days Overdue Formula | B11: =IF(Balance_Due=0, 0, MAX(0, Evaluation_Date - Due_Date))
A12: Aging Bucket Assignment (IFS) | B12: =IFS(Balance=0, "PAID IN FULL", Days=0, "Current", Days<=30, "1–30 Days", Days<=60, "31–60 Days", Days<=90, "61–90 Days", TRUE, "90+ Days")
A13: Expected Inflow Calculation | B13: = Balance_Due * Collection_Probability_%
A15: 4. Operational Guidelines | B15: Update the Evaluation_Date in cell B1 of Aging_Analysis weekly. And Record payments in AR_Invoice_Master under Amount_Paid to auto-adjust aging buckets and cash flow targets.
